flexhub/__init__.py
flexhub/_version.py
flexhub/batch_handler.py
flexhub-0.1.0.dist-info/WHEEL
flexhub-0.1.0.dist-info/METADATA
flexhub-0.1.0.dist-info/RECORD
