Metadata-Version: 2.4
Name: flexhub
Version: 0.1.0
Summary: Handler for batching messages to azure eventhubs
Requires-Python: >= 3.9
Requires-Dist: azure-eventhub>=5.15.0
Requires-Dist: azure-identity>=1.21.0
